{
  "documentIdentifier" : "BJNR004460952",
  "sections" : [
    {
      "documentIdentifier" : "BJNR004460952BJNG000101301",
      "laws" : [

      ],
      "sectionNumber" : {
        "numbers" : [
          1
        ]
      },
      "subsections" : [
        {
          "documentIdentifier" : "BJNR004460952BJNG000201301",
          "laws" : [
            {
              "documentIdentifier" : "BJNR004460952BJNE003701301",
              "paragraph" : "§ 1",
              "title" : "Ziel des Lastenausgleichs"
            },
            {
              "documentIdentifier" : "BJNR004460952BJNE003801301",
              "paragraph" : "§ 2",
              "title" : "Durchführung des Lastenausgleichs"
            },
            {
              "documentIdentifier" : "BJNR004460952BJNE003901301",
              "paragraph" : "§ 3",
              "title" : "Ausgleichsabgaben"
            },
            {
              "documentIdentifier" : "BJNR004460952BJNE004002301",
              "paragraph" : "§ 4",
              "title" : "Ausgleichsleistungen"
            },
            {
              "documentIdentifier" : "BJNR004460952BJNE004103301",
              "paragraph" : "§ 5",
              "title" : "Haushaltsmäßige Abwicklung"
            },
            {
              "documentIdentifier" : "BJNR004460952BJNE004202301",
              "paragraph" : "§ 6",
              "title" : "Beitrag der Länder zum Lastenausgleich"
            },
            {
              "documentIdentifier" : "BJNR004460952BJNE004302301",
              "paragraph" : "§ 7",
              "title" : "Kredite"
            }
          ],
          "sectionNumber" : {
            "numbers" : [
              1,
              1
            ]
          },
          "subsections" : [

          ],
          "title" : "Grundsätze"
        },
        {
          "documentIdentifier" : "BJNR004460952BJNG000301301",
          "laws" : [
            {
              "documentIdentifier" : "BJNR004460952BJNE004401301",
              "paragraph" : "§ 8",
              "title" : "Bezeichnung von Vorschriften"
            },
            {
              "documentIdentifier" : "BJNR004460952BJNE004501301",
              "paragraph" : "§ 9",
              "title" : "Sitz in Berlin (West)"
            },
            {
              "documentIdentifier" : "BJNR004460952BJNE004602308",
              "paragraph" : "§ 10",
              "title" : "Deutsche Mark und Euro"
            },
            {
              "documentIdentifier" : "BJNR004460952BJNE004702301",
              "paragraph" : "§ 11",
              "title" : "Vertriebener"
            },
            {
              "documentIdentifier" : "BJNR004460952BJNE004801301",
              "paragraph" : "§ 12",
              "title" : "Vertreibungsschäden"
            },
            {
              "documentIdentifier" : "BJNR004460952BJNE004901301",
              "paragraph" : "§ 13",
              "title" : "Kriegssachschäden"
            },
            {
              "documentIdentifier" : "BJNR004460952BJNE005001301",
              "paragraph" : "§ 14",
              "title" : "Ostschäden"
            },
            {
              "documentIdentifier" : "BJNR004460952BJNE005101301",
              "paragraph" : "§ 15",
              "title" : "Sparerschäden"
            },
            {
              "documentIdentifier" : "BJNR004460952BJNE005201301",
              "paragraph" : "§ 15a",
              "title" : "Zonenschäden"
            }
          ],
          "sectionNumber" : {
            "numbers" : [
              1,
              2
            ]
          },
          "subsections" : [

          ],
          "title" : "Begriffsbestimmungen"
        }
      ],
      "title" : "Grundsätze und Begriffsbestimmungen"
    },
    {
      "documentIdentifier" : "BJNR004460952BJNG000401301",
      "laws" : [
        {
          "documentIdentifier" : "BJNR004460952BJNE022401301",
          "paragraph" : "(XXXX) §§ 16 bis 227",
          "title" : "(nicht abgedruckt)"
        }
      ],
      "sectionNumber" : {
        "numbers" : [
          2
        ]
      },
      "subsections" : [
        {
          "documentIdentifier" : "BJNR004460952BJNG003500308",
          "laws" : [
            {
              "documentIdentifier" : "BJNR004460952BJNE022900308",
              "paragraph" : "§ 227a",
              "title" : "Anwendung des Zweiten Teils für den Zeitraum nach dem\n31. Dezember 2001"
            }
          ],
          "sectionNumber" : {
            "numbers" : [
              2,
              8
            ]
          },
          "subsections" : [

          ],
          "title" : "Achter Abschnitt"
        }
      ],
      "title" : "Ausgleichsabgaben"
    },
    {
      "documentIdentifier" : "BJNR004460952BJNG000501301",
      "laws" : [

      ],
      "sectionNumber" : {
        "numbers" : [
          3
        ]
      },
      "subsections" : [
        {
          "documentIdentifier" : "BJNR004460952BJNG000601301",
          "laws" : [
            {
              "documentIdentifier" : "BJNR004460952BJNE005301301",
              "paragraph" : "§ 228",
              "title" : "Schadenstatbestände"
            },
            {
              "documentIdentifier" : "BJNR004460952BJNE005402301",
              "paragraph" : "§ 229",
              "title" : "Geschädigte"
            },
            {
              "documentIdentifier" : "BJNR004460952BJNE005503301",
              "paragraph" : "§ 230",
              "title" : "Stichtag"
            },
            {
              "documentIdentifier" : "BJNR004460952BJNE005601301",
              "paragraph" : "§ 230a",
              "title" : "Besondere persönliche Voraussetzungen"
            },
            {
              "documentIdentifier" : "BJNR004460952BJNE005701301",
              "paragraph" : "§ 231",
              "title" : "Rechtsnatur der Ausgleichsleistungen"
            },
            {
              "documentIdentifier" : "BJNR004460952BJNE005802301",
              "paragraph" : "§ 232",
              "title" : "Ausgleichsleistungen mit Rechtsanspruch"
            },
            {
              "documentIdentifier" : "BJNR004460952BJNE005902301",
              "paragraph" : "§ 233",
              "title" : "Ausgleichsleistungen ohne Rechtsanspruch"
            },
            {
              "documentIdentifier" : "BJNR004460952BJNE022502301",
              "paragraph" : "§ 233a",
              "title" : "Verjährung"
            },
            {
              "documentIdentifier" : "BJNR004460952BJNE006003301",
              "paragraph" : "§ 234",
              "title" : "Antrag"
            }
          ],
          "sectionNumber" : {
            "numbers" : [
              3,
              1
            ]
          },
          "subsections" : [

          ],
          "title" : "Allgemeine Vorschriften"
        },
        {
          "documentIdentifier" : "BJNR004460952BJNG000701301",
          "laws" : [

          ],
          "sectionNumber" : {
            "numbers" : [
              3,
              2
            ]
          },
          "subsections" : [
            {
              "documentIdentifier" : "BJNR004460952BJNG000801301",
              "laws" : [
                {
                  "documentIdentifier" : "BJNR004460952BJNE006101301",
                  "paragraph" : "§ 235",
                  "title" : "Schadensfeststellung als Voraussetzung\nvon Ausgleichsleistungen"
                },
                {
                  "documentIdentifier" : "BJNR004460952BJNE006201301",
                  "paragraph" : "§ 236",
                  "title" : "Schadensfeststellung nach dem Feststellungsgesetz\nund nach dem Beweissicherungs- und Feststellungsgesetz"
                },
                {
                  "documentIdentifier" : "BJNR004460952BJNE006301301",
                  "paragraph" : "§ 237",
                  "title" : "Schadensfeststellung außerhalb des\nFeststellungsgesetzes"
                }
              ],
              "sectionNumber" : {
                "numbers" : [
                  3,
                  2,
                  1
                ]
              },
              "subsections" : [

              ],
              "title" : "Grundsätze"
            },
            {
              "documentIdentifier" : "BJNR004460952BJNG000901301",
              "laws" : [
                {
                  "documentIdentifier" : "BJNR004460952BJNE006401301",
                  "paragraph" : "§ 238",
                  "title" : "Schadensberechnung nach dem\nFeststellungsgesetz und nach dem\nBeweissicherungs- und Feststellungsgesetz"
                },
                {
                  "documentIdentifier" : "BJNR004460952BJNE006501301",
                  "paragraph" : "§ 239",
                  "title" : "Schadensberechnung bei Verlust der beruflichen\noder sonstigen Existenzgrundlage"
                },
                {
                  "documentIdentifier" : "BJNR004460952BJNE006601301",
                  "paragraph" : "§ 240",
                  "title" : "Schadensberechnung bei Sparerschäden"
                },
                {
                  "documentIdentifier" : "BJNR004460952BJNE006801301",
                  "paragraph" : "§ 242",
                  "title" : "Zusammenfassung der Einzelfeststellungen"
                }
              ],
              "sectionNumber" : {
                "numbers" : [
                  3,
                  2,
                  2
                ]
              },
              "subsections" : [

              ],
              "title" : "Schadensberechnung"
            }
          ],
          "title" : "Feststellung von Schäden"
        },
        {
          "documentIdentifier" : "BJNR004460952BJNG001001301",
          "laws" : [
            {
              "documentIdentifier" : "BJNR004460952BJNE006901301",
              "paragraph" : "§ 243",
              "title" : "Voraussetzungen"
            },
            {
              "documentIdentifier" : "BJNR004460952BJNE007001301",
              "paragraph" : "§ 244",
              "title" : "Übertragbarkeit"
            },
            {
              "documentIdentifier" : "BJNR004460952BJNE007101301",
              "paragraph" : "§ 245",
              "title" : "Schadensbetrag"
            },
            {
              "documentIdentifier" : "BJNR004460952BJNE007202308",
              "paragraph" : "§ 246",
              "title" : "Schadensgruppen und Grundbeträge"
            },
            {
              "documentIdentifier" : "BJNR004460952BJNE007301301",
              "paragraph" : "§ 247",
              "title" : "Teilung des Grundbetrags"
            },
            {
              "documentIdentifier" : "BJNR004460952BJNE007401301",
              "paragraph" : "§ 248",
              "title" : "Zuschlag zum Grundbetrag"
            },
            {
              "documentIdentifier" : "BJNR004460952BJNE007502308",
              "paragraph" : "§ 249",
              "title" : "Kürzung des Grundbetrags"
            },
            {
              "documentIdentifier" : "BJNR004460952BJNE007602308",
              "paragraph" : "§ 249a",
              "title" : "Sparerzuschlag"
            },
            {
              "documentIdentifier" : "BJNR004460952BJNE007701301",
              "paragraph" : "§ 249b",
              "title" : "Besonderheiten der Grundbetragsberechnung\nbeim Zusammentreffen von Zonenschäden mit Schäden\nim Sinne des Reparationsschädengesetzes"
            },
            {
              "documentIdentifier" : "BJNR004460952BJNE007802308",
              "paragraph" : "§ 250",
              "title" : "Zuerkennung des Anspruchs und Zinszuschlag"
            },
            {
              "documentIdentifier" : "BJNR004460952BJNE007903301",
              "paragraph" : "§ 251",
              "title" : "Erfüllung des Anspruchs"
            },
            {
              "documentIdentifier" : "BJNR004460952BJNE008002301",
              "paragraph" : "§ 252",
              "title" : "Reihenfolge und Zeitpunkt der Erfüllung"
            }
          ],
          "sectionNumber" : {
            "numbers" : [
              3,
              3
            ]
          },
          "subsections" : [

          ],
          "title" : "Hauptentschädigung"
        },
        {
          "documentIdentifier" : "BJNR004460952BJNG001101301",
          "laws" : [

          ],
          "sectionNumber" : {
            "numbers" : [
              3,
              4
            ]
          },
          "subsections" : [
            {
              "documentIdentifier" : "BJNR004460952BJNG001201301",
              "laws" : [
                {
                  "documentIdentifier" : "BJNR004460952BJNE008102301",
                  "paragraph" : "(XXXX) §§ 253 bis 257",
                  "title" : "(weggefallen)"
                }
              ],
              "sectionNumber" : {
                "numbers" : [
                  3,
                  4,
                  1
                ]
              },
              "subsections" : [

              ],
              "title" : "Allgemeine Vorschriften"
            },
            {
              "documentIdentifier" : "BJNR004460952BJNG001301301",
              "laws" : [
                {
                  "documentIdentifier" : "BJNR004460952BJNE008602301",
                  "paragraph" : "§ 258",
                  "title" : "Verhältnis zur Hauptentschädigung"
                }
              ],
              "sectionNumber" : {
                "numbers" : [
                  3,
                  4,
                  2
                ]
              },
              "subsections" : [

              ],
              "title" : "Eingliederungsdarlehen an einzelne Geschädigte (Aufbaudarlehen)"
            },
            {
              "documentIdentifier" : "BJNR004460952BJNG001401301",
              "laws" : [
                {
                  "documentIdentifier" : "BJNR004460952BJNE008702301",
                  "paragraph" : "(XXXX) §§ 259 und 260",
                  "title" : "(weggefallen)"
                }
              ],
              "sectionNumber" : {
                "numbers" : [
                  3,
                  4,
                  3
                ]
              },
              "subsections" : [

              ],
              "title" : "Eingliederungsdarlehen zur Schaffung von Dauerarbeitsplätzen (Arbeitsplatzdarlehen)"
            }
          ],
          "title" : "Eingliederungsdarlehen"
        },
        {
          "documentIdentifier" : "BJNR004460952BJNG001501301",
          "laws" : [

          ],
          "sectionNumber" : {
            "numbers" : [
              3,
              5
            ]
          },
          "subsections" : [
            {
              "documentIdentifier" : "BJNR004460952BJNG001601301",
              "laws" : [
                {
                  "documentIdentifier" : "BJNR004460952BJNE008902301",
                  "paragraph" : "§ 261",
                  "title" : "Voraussetzungen"
                },
                {
                  "documentIdentifier" : "BJNR004460952BJNE009001301",
                  "paragraph" : "§ 262",
                  "title" : "Übertragbarkeit"
                },
                {
                  "documentIdentifier" : "BJNR004460952BJNE009103301",
                  "paragraph" : "§ 263",
                  "title" : "Formen der Kriegsschadenrente"
                },
                {
                  "documentIdentifier" : "BJNR004460952BJNE009202301",
                  "paragraph" : "§ 264",
                  "title" : "Lebensalter"
                },
                {
                  "documentIdentifier" : "BJNR004460952BJNE009306160",
                  "paragraph" : "§ 265",
                  "title" : "Erwerbsunfähigkeit"
                },
                {
                  "documentIdentifier" : "BJNR004460952BJNE009401301",
                  "paragraph" : "§ 266",
                  "title" : "Ermittlung des Schadens und des Grundbetrags"
                }
              ],
              "sectionNumber" : {
                "numbers" : [
                  3,
                  5,
                  1
                ]
              },
              "subsections" : [

              ],
              "title" : "Allgemeine Vorschriften"
            },
            {
              "documentIdentifier" : "BJNR004460952BJNG001701301",
              "laws" : [
                {
                  "documentIdentifier" : "BJNR004460952BJNE009517301",
                  "paragraph" : "§ 267",
                  "title" : "Einkommenshöchstbetrag"
                },
                {
                  "documentIdentifier" : "BJNR004460952BJNE009710301",
                  "paragraph" : "§ 269",
                  "title" : "Höhe der Unterhaltshilfe"
                },
                {
                  "documentIdentifier" : "BJNR004460952BJNE009812301",
                  "paragraph" : "§ 269a",
                  "title" : "Selbständigenzuschlag"
                },
                {
                  "documentIdentifier" : "BJNR004460952BJNE009908301",
                  "paragraph" : "§ 269b",
                  "title" : "Sozialzuschlag"
                },
                {
                  "documentIdentifier" : "BJNR004460952BJNE010003308",
                  "paragraph" : "§ 270",
                  "title" : "Anrechnung von Einkünften"
                },
                {
                  "documentIdentifier" : "BJNR004460952BJNE010201301",
                  "paragraph" : "§ 271",
                  "title" : "Dauer der Unterhaltshilfe"
                },
                {
                  "documentIdentifier" : "BJNR004460952BJNE010302308",
                  "paragraph" : "§ 272",
                  "title" : "Unterhaltshilfe auf Lebenszeit"
                },
                {
                  "documentIdentifier" : "BJNR004460952BJNE010402308",
                  "paragraph" : "§ 273",
                  "title" : "Unterhaltshilfe auf Zeit"
                },
                {
                  "documentIdentifier" : "BJNR004460952BJNE010511301",
                  "paragraph" : "§ 274",
                  "title" : "Sonderregelung bei Wegfall öffentlicher Renten"
                },
                {
                  "documentIdentifier" : "BJNR004460952BJNE010610301",
                  "paragraph" : "§ 275",
                  "title" : "Unterhaltshilfe für Vollwaisen"
                },
                {
                  "documentIdentifier" : "BJNR004460952BJNE010718301",
                  "paragraph" : "§ 276",
                  "title" : "Krankenversorgung, Pflegeversicherung"
                },
                {
                  "documentIdentifier" : "BJNR004460952BJNE010905301",
                  "paragraph" : "§ 277",
                  "title" : "Sterbegeld"
                },
                {
                  "documentIdentifier" : "BJNR004460952BJNE011102308",
                  "paragraph" : "§ 278",
                  "title" : "Verhältnis zur Entschädigungsrente"
                },
                {
                  "documentIdentifier" : "BJNR004460952BJNE011204301",
                  "paragraph" : "§ 278a",
                  "title" : "Verhältnis zur Hauptentschädigung"
                }
              ],
              "sectionNumber" : {
                "numbers" : [
                  3,
                  5,
                  2
                ]
              },
              "subsections" : [

              ],
              "title" : "Unterhaltshilfe"
            },
            {
              "documentIdentifier" : "BJNR004460952BJNG001801301",
              "laws" : [
                {
                  "documentIdentifier" : "BJNR004460952BJNE011310301",
                  "paragraph" : "§ 279",
                  "title" : "Einkommenshöchstbetrag"
                },
                {
                  "documentIdentifier" : "BJNR004460952BJNE011403308",
                  "paragraph" : "§ 280",
                  "title" : "Höhe der Entschädigungsrente"
                },
                {
                  "documentIdentifier" : "BJNR004460952BJNE011502308",
                  "paragraph" : "§ 281",
                  "title" : "Vorauszahlungen auf die Entschädigungsrente"
                },
                {
                  "documentIdentifier" : "BJNR004460952BJNE011602308",
                  "paragraph" : "§ 282",
                  "title" : "Besondere Voraussetzungen der Entschädigungsrente"
                },
                {
                  "documentIdentifier" : "BJNR004460952BJNE011703301",
                  "paragraph" : "§ 283",
                  "title" : "Verhältnis zur Hauptentschädigung"
                },
                {
                  "documentIdentifier" : "BJNR004460952BJNE011802301",
                  "paragraph" : "§ 283a",
                  "title" : "Verhältnis zur Hauptentschädigung bei\ngleichzeitigem Bezug von Unterhaltshilfe"
                },
                {
                  "documentIdentifier" : "BJNR004460952BJNE011902308",
                  "paragraph" : "§ 284",
                  "title" : "Sonderregelung bei Verlust der beruflichen\noder sonstigen Existenzgrundlage"
                },
                {
                  "documentIdentifier" : "BJNR004460952BJNE012001301",
                  "paragraph" : "§ 285",
                  "title" : "Dauer der Entschädigungsrente"
                }
              ],
              "sectionNumber" : {
                "numbers" : [
                  3,
                  5,
                  3
                ]
              },
              "subsections" : [

              ],
              "title" : "Entschädigungsrente"
            },
            {
              "documentIdentifier" : "BJNR004460952BJNG001901301",
              "laws" : [
                {
                  "documentIdentifier" : "BJNR004460952BJNE012101301",
                  "paragraph" : "§ 286",
                  "title" : "Zuerkennung des Anspruchs auf Kriegsschadenrente"
                },
                {
                  "documentIdentifier" : "BJNR004460952BJNE012204301",
                  "paragraph" : "§ 287",
                  "title" : "Erfüllung des Anspruchs auf Kriegsschadenrente"
                },
                {
                  "documentIdentifier" : "BJNR004460952BJNE012301301",
                  "paragraph" : "§ 288",
                  "title" : "Wirkung von Veränderungen"
                },
                {
                  "documentIdentifier" : "BJNR004460952BJNE012401301",
                  "paragraph" : "§ 289",
                  "title" : "Meldepflicht"
                },
                {
                  "documentIdentifier" : "BJNR004460952BJNE012506301",
                  "paragraph" : "§ 290",
                  "title" : "Erstattungspflicht"
                },
                {
                  "documentIdentifier" : "BJNR004460952BJNE012601301",
                  "paragraph" : "§ 291",
                  "title" : "Verhältnis zu Aufbaudarlehen"
                },
                {
                  "documentIdentifier" : "BJNR004460952BJNE012718301",
                  "paragraph" : "§ 292",
                  "title" : "Verhältnis zur Sozialhilfe, zur Kriegsopferfürsorge\nsowie zur Arbeitslosenversicherung und zu Leistungen zur Sicherung\ndes Lebensunterhalts"
                }
              ],
              "sectionNumber" : {
                "numbers" : [
                  3,
                  5,
                  4
                ]
              },
              "subsections" : [

              ],
              "title" : "Gemeinsame Vorschriften"
            },
            {
              "documentIdentifier" : "BJNR004460952BJNG003600301",
              "laws" : [
                {
                  "documentIdentifier" : "BJNR004460952BJNE023002160",
                  "paragraph" : "§ 292a",
                  "title" : "Bestimmungen zur Unterhaltshilfe und Entschädigungsrente"
                },
                {
                  "documentIdentifier" : "BJNR004460952BJNE023100301",
                  "paragraph" : "§ 292b",
                  "title" : "Sterbegeld"
                },
                {
                  "documentIdentifier" : "BJNR004460952BJNE023200301",
                  "paragraph" : "§ 292c",
                  "title" : "Überleitungsvorschriften"
                }
              ],
              "sectionNumber" : {
                "numbers" : [
                  3,
                  5,
                  5
                ]
              },
              "subsections" : [

              ],
              "title" : "Vorschriften für die Zahlung der Kriegsschadenrente nach dem 31. Dezember 2005"
            }
          ],
          "title" : "Kriegsschadenrente"
        },
        {
          "documentIdentifier" : "BJNR004460952BJNG002001301",
          "laws" : [
            {
              "documentIdentifier" : "BJNR004460952BJNE012801301",
              "paragraph" : "§ 293",
              "title" : "Voraussetzungen"
            },
            {
              "documentIdentifier" : "BJNR004460952BJNE012901301",
              "paragraph" : "§ 294",
              "title" : "Übertragbarkeit"
            },
            {
              "documentIdentifier" : "BJNR004460952BJNE013002308",
              "paragraph" : "§ 295",
              "title" : "Zuerkennung und Höhe des Anspruchs"
            },
            {
              "documentIdentifier" : "BJNR004460952BJNE013102308",
              "paragraph" : "§ 296",
              "title" : "Anrechnung früherer Zahlungen"
            },
            {
              "documentIdentifier" : "BJNR004460952BJNE013201301",
              "paragraph" : "§ 297",
              "title" : "Erfüllung des Anspruchs"
            }
          ],
          "sectionNumber" : {
            "numbers" : [
              3,
              6
            ]
          },
          "subsections" : [

          ],
          "title" : "Hausratentschädigung"
        },
        {
          "documentIdentifier" : "BJNR004460952BJNG002101301",
          "laws" : [
            {
              "documentIdentifier" : "BJNR004460952BJNE013301301",
              "paragraph" : "§ 298",
              "title" : "Voraussetzungen"
            },
            {
              "documentIdentifier" : "BJNR004460952BJNE013401301",
              "paragraph" : "§ 299",
              "title" : "Grundsätze"
            },
            {
              "documentIdentifier" : "BJNR004460952BJNE013501301",
              "paragraph" : "§ 300",
              "title" : "Einsatz der Mittel"
            }
          ],
          "sectionNumber" : {
            "numbers" : [
              3,
              7
            ]
          },
          "subsections" : [

          ],
          "title" : "Wohnraumhilfe"
        },
        {
          "documentIdentifier" : "BJNR004460952BJNG002202301",
          "laws" : [
            {
              "documentIdentifier" : "BJNR004460952BJNE013602301",
              "paragraph" : "§ 301",
              "title" : "Allgemeine Vorschriften"
            },
            {
              "documentIdentifier" : "BJNR004460952BJNE013702301",
              "paragraph" : "§ 301a",
              "title" : "Leistungen an Sowjetzonenflüchtlinge"
            },
            {
              "documentIdentifier" : "BJNR004460952BJNE013803160",
              "paragraph" : "§ 301b",
              "title" : "Leistungen in außergewöhnlichen Härtefällen"
            }
          ],
          "sectionNumber" : {
            "numbers" : [
              3,
              8
            ]
          },
          "subsections" : [

          ],
          "title" : "Härteleistungen"
        },
        {
          "documentIdentifier" : "BJNR004460952BJNG002301301",
          "laws" : [
            {
              "documentIdentifier" : "BJNR004460952BJNE013901301",
              "paragraph" : "§ 302",
              "title" : "Bereitstellung von Mitteln"
            }
          ],
          "sectionNumber" : {
            "numbers" : [
              3,
              9
            ]
          },
          "subsections" : [

          ],
          "title" : "Sonstige Förderungsmaßnahmen"
        },
        {
          "documentIdentifier" : "BJNR004460952BJNG002401301",
          "laws" : [

          ],
          "sectionNumber" : {
            "numbers" : [
              3,
              10
            ]
          },
          "subsections" : [

          ],
          "title" : "Zehnter Abschnitt"
        },
        {
          "documentIdentifier" : "BJNR004460952BJNG002502301",
          "laws" : [
            {
              "documentIdentifier" : "BJNR004460952BJNE014201301",
              "paragraph" : "§ 305",
              "title" : "Auftragsverwaltung"
            },
            {
              "documentIdentifier" : "BJNR004460952BJNE014302301",
              "paragraph" : "§ 306",
              "title" : "Landesbehörden"
            },
            {
              "documentIdentifier" : "BJNR004460952BJNE014401301",
              "paragraph" : "§ 307",
              "title" : "Bundesoberbehörde"
            },
            {
              "documentIdentifier" : "BJNR004460952BJNE014504308",
              "paragraph" : "§ 308",
              "title" : "Ausgleichsämter"
            },
            {
              "documentIdentifier" : "BJNR004460952BJNE014703301",
              "paragraph" : "§ 310",
              "title" : "Beschwerdeausschüsse"
            },
            {
              "documentIdentifier" : "BJNR004460952BJNE014802301",
              "paragraph" : "§ 311",
              "title" : "Landesausgleichsämter"
            },
            {
              "documentIdentifier" : "BJNR004460952BJNE014905311",
              "paragraph" : "§ 312",
              "title" : "Bundesausgleichsamt"
            },
            {
              "documentIdentifier" : "BJNR004460952BJNE015003377",
              "paragraph" : "§ 313",
              "title" : "Zuständigkeitsübertragung"
            },
            {
              "documentIdentifier" : "BJNR004460952BJNE015202301",
              "paragraph" : "§ 315",
              "title" : "Allgemeine Verwaltungsgerichte"
            },
            {
              "documentIdentifier" : "BJNR004460952BJNE015406116",
              "paragraph" : "§ 317",
              "title" : "Amts- und Rechtshilfe sowie Auskunftspflicht"
            }
          ],
          "sectionNumber" : {
            "numbers" : [
              3,
              11
            ]
          },
          "subsections" : [

          ],
          "title" : "Organisation und Zuständigkeit"
        },
        {
          "documentIdentifier" : "BJNR004460952BJNG002602301",
          "laws" : [
            {
              "documentIdentifier" : "BJNR004460952BJNE015602301",
              "paragraph" : "§ 319",
              "title" : "Aufgaben des Präsidenten des Bundesausgleichsamtes"
            },
            {
              "documentIdentifier" : "BJNR004460952BJNE016003301",
              "paragraph" : "§ 323",
              "title" : "Sondervorschriften über die Verwendung von Mitteln"
            }
          ],
          "sectionNumber" : {
            "numbers" : [
              3,
              12
            ]
          },
          "subsections" : [

          ],
          "title" : "Verwaltung der Mittel für den Lastenausgleich"
        },
        {
          "documentIdentifier" : "BJNR004460952BJNG002701301",
          "laws" : [

          ],
          "sectionNumber" : {
            "numbers" : [
              3,
              13
            ]
          },
          "subsections" : [
            {
              "documentIdentifier" : "BJNR004460952BJNG002801301",
              "laws" : [
                {
                  "documentIdentifier" : "BJNR004460952BJNE016201301",
                  "paragraph" : "§ 325",
                  "title" : "Antragstellung"
                },
                {
                  "documentIdentifier" : "BJNR004460952BJNE016303301",
                  "paragraph" : "§ 326",
                  "title" : "Weiterbehandlung der Anträge"
                },
                {
                  "documentIdentifier" : "BJNR004460952BJNE016403308",
                  "paragraph" : "§ 327",
                  "title" : "Vertretung"
                },
                {
                  "documentIdentifier" : "BJNR004460952BJNE016502301",
                  "paragraph" : "§ 328",
                  "title" : "Ausschließung von der Mitwirkung am Verfahren"
                },
                {
                  "documentIdentifier" : "BJNR004460952BJNE016602301",
                  "paragraph" : "§ 329",
                  "title" : "Verbindung von Verfahren"
                },
                {
                  "documentIdentifier" : "BJNR004460952BJNE016702301",
                  "paragraph" : "§ 330",
                  "title" : "Beweiserhebung"
                },
                {
                  "documentIdentifier" : "BJNR004460952BJNE022102308",
                  "paragraph" : "§ 330a",
                  "title" : "Mitwirkungspflichten"
                },
                {
                  "documentIdentifier" : "BJNR004460952BJNE016802301",
                  "paragraph" : "§ 331",
                  "title" : "Beweiswürdigung"
                },
                {
                  "documentIdentifier" : "BJNR004460952BJNE016906301",
                  "paragraph" : "§ 332",
                  "title" : "Entscheidungen"
                },
                {
                  "documentIdentifier" : "BJNR004460952BJNE022203301",
                  "paragraph" : "§ 332a",
                  "title" : "Aufgebotsverfahren"
                },
                {
                  "documentIdentifier" : "BJNR004460952BJNE017001301",
                  "paragraph" : "§ 333",
                  "title" : "Verfahren vor den Verwaltungsgerichten"
                },
                {
                  "documentIdentifier" : "BJNR004460952BJNE017102301",
                  "paragraph" : "§ 334",
                  "title" : "Gebühren und Kosten"
                }
              ],
              "sectionNumber" : {
                "numbers" : [
                  3,
                  13,
                  1
                ]
              },
              "subsections" : [

              ],
              "title" : "Allgemeine Vorschriften"
            },
            {
              "documentIdentifier" : "BJNR004460952BJNG002901301",
              "laws" : [
                {
                  "documentIdentifier" : "BJNR004460952BJNE017303301",
                  "paragraph" : "§ 335",
                  "title" : "Bescheid"
                },
                {
                  "documentIdentifier" : "BJNR004460952BJNE017401301",
                  "paragraph" : "§ 335a",
                  "title" : "Bescheid unter Vorbehalt"
                },
                {
                  "documentIdentifier" : "BJNR004460952BJNE022800301",
                  "paragraph" : "§ 335b",
                  "title" : "Verfahren bei Schadensausgleich an Beteiligungen"
                },
                {
                  "documentIdentifier" : "BJNR004460952BJNE017503301",
                  "paragraph" : "§ 336",
                  "title" : "Beschwerde"
                },
                {
                  "documentIdentifier" : "BJNR004460952BJNE017601301",
                  "paragraph" : "§ 337",
                  "title" : "Beschluß des Beschwerdeausschusses"
                },
                {
                  "documentIdentifier" : "BJNR004460952BJNE017803301",
                  "paragraph" : "§ 338",
                  "title" : "Anfechtungsklage beim Verwaltungsgericht"
                },
                {
                  "documentIdentifier" : "BJNR004460952BJNE017903301",
                  "paragraph" : "§ 339",
                  "title" : "Rechtsmittel gegen Entscheidungen des Verwaltungsgerichts"
                },
                {
                  "documentIdentifier" : "BJNR004460952BJNE018003301",
                  "paragraph" : "§ 340",
                  "title" : "Aufschiebende Wirkung"
                },
                {
                  "documentIdentifier" : "BJNR004460952BJNE018102301",
                  "paragraph" : "§ 341",
                  "title" : "Wiedereinsetzung in den vorigen Stand"
                },
                {
                  "documentIdentifier" : "BJNR004460952BJNE018205301",
                  "paragraph" : "§ 342",
                  "title" : "Wiederaufnahme des Verfahrens"
                },
                {
                  "documentIdentifier" : "BJNR004460952BJNE018304301",
                  "paragraph" : "§ 343",
                  "title" : "Erlöschen, Einstellung und Rückforderung der Kriegsschadenrente"
                },
                {
                  "documentIdentifier" : "BJNR004460952BJNE018401301",
                  "paragraph" : "§ 344",
                  "title" : "Feststellungsverfahren"
                }
              ],
              "sectionNumber" : {
                "numbers" : [
                  3,
                  13,
                  2
                ]
              },
              "subsections" : [

              ],
              "title" : "Verfahren bei Hauptentschädigung, Kriegsschadenrente und Hausratentschädigung"
            },
            {
              "documentIdentifier" : "BJNR004460952BJNG003002301",
              "laws" : [
                {
                  "documentIdentifier" : "BJNR004460952BJNE018504301",
                  "paragraph" : "§ 345",
                  "title" : "Grundsatzregelung"
                },
                {
                  "documentIdentifier" : "BJNR004460952BJNE018601301",
                  "paragraph" : "§ 346",
                  "title" : "Besondere Regelung"
                }
              ],
              "sectionNumber" : {
                "numbers" : [
                  3,
                  13,
                  3
                ]
              },
              "subsections" : [

              ],
              "title" : "Verfahren bei Erfüllung von Ansprüchen auf Hauptentschädigung und Hausratentschädigung sowie bei Eingliederungsdarlehen, Härteleistungen und auf Grund sonstiger Förderungsmaßnahmen"
            },
            {
              "documentIdentifier" : "BJNR004460952BJNG003101301",
              "laws" : [
                {
                  "documentIdentifier" : "BJNR004460952BJNE018701301",
                  "paragraph" : "§ 347",
                  "title" : "Entscheidung des Ausgleichsausschusses"
                },
                {
                  "documentIdentifier" : "BJNR004460952BJNE018801301",
                  "paragraph" : "§ 348",
                  "title" : "Zuteilung der Mittel"
                }
              ],
              "sectionNumber" : {
                "numbers" : [
                  3,
                  13,
                  4
                ]
              },
              "subsections" : [

              ],
              "title" : "Verfahren bei der Wohnraumhilfe"
            }
          ],
          "title" : "Verfahren"
        },
        {
          "documentIdentifier" : "BJNR004460952BJNG003201301",
          "laws" : [
            {
              "documentIdentifier" : "BJNR004460952BJNE018912377",
              "paragraph" : "§ 349",
              "title" : "Rückforderung bei Schadensausgleich"
            },
            {
              "documentIdentifier" : "BJNR004460952BJNE023300301",
              "paragraph" : "§ 349a",
              "title" : "Mindestbetrag für Rückforderungen"
            }
          ],
          "sectionNumber" : {
            "numbers" : [
              3,
              14
            ]
          },
          "subsections" : [

          ],
          "title" : "Vierzehnter Abschnitt"
        },
        {
          "documentIdentifier" : "BJNR004460952BJNG003301301",
          "laws" : [
            {
              "documentIdentifier" : "BJNR004460952BJNE019002301",
              "paragraph" : "§ 350",
              "title" : "Ehrenamtliche Mitarbeit"
            },
            {
              "documentIdentifier" : "BJNR004460952BJNE019105301",
              "paragraph" : "§ 350a",
              "title" : "Erstattung und Verrechnung von Ausgleichsleistungen"
            },
            {
              "documentIdentifier" : "BJNR004460952BJNE019203301",
              "paragraph" : "§ 350b",
              "title" : "Fälligkeit, Stundung und Vollstreckung"
            },
            {
              "documentIdentifier" : "BJNR004460952BJNE019303301",
              "paragraph" : "§ 350c",
              "title" : "Verzinsung, Säumniszuschläge und Auslagen"
            },
            {
              "documentIdentifier" : "BJNR004460952BJNE019402301",
              "paragraph" : "§ 350d",
              "title" : "Abgabe und Entgegennahme von Erklärungen für\nden Bund"
            },
            {
              "documentIdentifier" : "BJNR004460952BJNE022301301",
              "paragraph" : "§ 350e",
              "title" : "Überleitung von Rechtsbehelfsverfahren"
            },
            {
              "documentIdentifier" : "BJNR004460952BJNE019502301",
              "paragraph" : "§ 351",
              "title" : "Verwaltungskosten"
            },
            {
              "documentIdentifier" : "BJNR004460952BJNE020201301",
              "paragraph" : "§ 358",
              "title" : "Sondervorschriften für Berlin"
            }
          ],
          "sectionNumber" : {
            "numbers" : [
              3,
              15
            ]
          },
          "subsections" : [

          ],
          "title" : "Sonstige und Überleitungsvorschriften"
        }
      ],
      "title" : "Ausgleichsleistungen"
    },
    {
      "documentIdentifier" : "BJNR004460952BJNG003401301",
      "laws" : [
        {
          "documentIdentifier" : "BJNR004460952BJNE020301301",
          "paragraph" : "§ 359",
          "title" : "Nichtberücksichtigung von Schäden und Verlusten,\nRückerstattungsfälle"
        },
        {
          "documentIdentifier" : "BJNR004460952BJNE020404301",
          "paragraph" : "§ 360",
          "title" : "Ausschließung von Ausgleichsleistungen und Vergünstigungen"
        },
        {
          "documentIdentifier" : "BJNR004460952BJNE020501301",
          "paragraph" : "§ 361",
          "title" : "Vertragshilfe"
        },
        {
          "documentIdentifier" : "BJNR004460952BJNE020601301",
          "paragraph" : "§ 362",
          "title" : "Vollstreckungsschutz wegen alter Verbindlichkeiten"
        },
        {
          "documentIdentifier" : "BJNR004460952BJNE020704301",
          "paragraph" : "§ 363",
          "title" : "Schutz gegen Inanspruchnahme aus Leistungen der Sozialhilfe\noder Grundsicherung für Arbeitsuchende"
        },
        {
          "documentIdentifier" : "BJNR004460952BJNE020801301",
          "paragraph" : "§ 364",
          "title" : "Ergänzende Maßnahmen"
        },
        {
          "documentIdentifier" : "BJNR004460952BJNE020902301",
          "paragraph" : "§ 365",
          "title" : "Altsparerregelung"
        },
        {
          "documentIdentifier" : "BJNR004460952BJNE021101301",
          "paragraph" : "§ 367",
          "title" : "Erlaß von Rechtsverordnungen"
        },
        {
          "documentIdentifier" : "BJNR004460952BJNE021702301",
          "paragraph" : "§ 373",
          "title" : "Übergangsvorschrift aus Anlass des Gesetzes\nzur Änderung und Bereinigung des Lastenausgleichsrechts"
        },
        {
          "documentIdentifier" : "BJNR004460952BJNE021801301",
          "paragraph" : "§ 374",
          "title" : "Anwendung des Gesetzes in Berlin"
        },
        {
          "documentIdentifier" : "BJNR004460952BJNE888801301",
          "paragraph" : "Anhang EV",
          "title" : "Auszug aus EinigVtr Anlage I Kapitel II Sachgebiet D Abschnitt III"
        }
      ],
      "sectionNumber" : {
        "numbers" : [
          4
        ]
      },
      "subsections" : [

      ],
      "title" : "Gemeinsame Schlußvorschriften"
    }
  ]
}