{
  "documentIdentifier" : "BJNR054510997",
  "sections" : [
    {
      "documentIdentifier" : "BJNR054510997Content",
      "laws" : [
        {
          "documentIdentifier" : "BJNR054510997BJNE000100320",
          "paragraph" : "§ 1",
          "title" : "Anwendungsbereich"
        },
        {
          "documentIdentifier" : "BJNR054510997BJNE000200320",
          "paragraph" : "§ 2",
          "title" : "Begriffsbestimmung"
        },
        {
          "documentIdentifier" : "BJNR054510997BJNE000300320",
          "paragraph" : "§ 3",
          "title" : "Feuerung"
        },
        {
          "documentIdentifier" : "BJNR054510997BJNE000400320",
          "paragraph" : "§ 4",
          "title" : "Emissionsgrenzwerte"
        },
        {
          "documentIdentifier" : "BJNR054510997BJNE000500320",
          "paragraph" : "§ 5",
          "title" : "Ableitbedingungen für Abgase"
        },
        {
          "documentIdentifier" : "BJNR054510997BJNE000600320",
          "paragraph" : "§ 6",
          "title" : "Anzeige"
        },
        {
          "documentIdentifier" : "BJNR054510997BJNE000701320",
          "paragraph" : "§ 7",
          "title" : "Kontinuierliche Messungen"
        },
        {
          "documentIdentifier" : "BJNR054510997BJNE000800320",
          "paragraph" : "§ 8",
          "title" : "Beurteilung und Berichte von kontinuierlichen\nMessungen"
        },
        {
          "documentIdentifier" : "BJNR054510997BJNE000901116",
          "paragraph" : "§ 9",
          "title" : "Einzelmessungen"
        },
        {
          "documentIdentifier" : "BJNR054510997BJNE001000320",
          "paragraph" : "§ 10",
          "title" : "Beurteilung und Berichte von Einzelmessungen"
        },
        {
          "documentIdentifier" : "BJNR054510997BJNE001100320",
          "paragraph" : "§ 11",
          "title" : "Übergangsregelung"
        },
        {
          "documentIdentifier" : "BJNR054510997BJNE001200320",
          "paragraph" : "§ 12",
          "title" : "Zulassung von Ausnahmen"
        },
        {
          "documentIdentifier" : "BJNR054510997BJNE001300320",
          "paragraph" : "§ 13",
          "title" : "Weitergehende Anforderungen"
        },
        {
          "documentIdentifier" : "BJNR054510997BJNE001400320",
          "paragraph" : "§ 14",
          "title" : "Ordnungswidrigkeiten"
        },
        {
          "documentIdentifier" : "BJNR054510997BJNE001500320",
          "paragraph" : "Anhang 1",
          "title" : "Bestimmung der Massenkonzentration von Gesamtstaub und\nund Gesamtkohlenstoff nach § 4 Nr. 2"
        },
        {
          "documentIdentifier" : "BJNR054510997BJNE001600320",
          "paragraph" : "Anhang 2",
          "title" : "Bestimmung der Massenkonzentration von Dioxinen\nund Furanen nach § 4 Nr. 3"
        }
      ],
      "sectionNumber" : {
        "numbers" : [
          1
        ]
      },
      "subsections" : [

      ],
      "title" : "Inhalt"
    }
  ]
}