{
  "documentIdentifier" : "BJNR390800994",
  "sections" : [
    {
      "documentIdentifier" : "BJNR390800994Content",
      "laws" : [
        {
          "documentIdentifier" : "BJNR390800994BJNE000204377",
          "paragraph" : "§ 1",
          "title" : "Übertragung von Aufgaben"
        },
        {
          "documentIdentifier" : "BJNR390800994BJNE000301307",
          "paragraph" : "§ 2",
          "title" : "Übertragung von Unternehmensbeteiligungen"
        },
        {
          "documentIdentifier" : "BJNR390800994BJNE000400000",
          "paragraph" : "§ 3",
          "title" : "Inkrafttreten"
        },
        {
          "documentIdentifier" : "BJNR390800994BJNE000501307",
          "paragraph" : "Anlage 1",
          "title" : "(zu § 2 Abs. 2)"
        },
        {
          "documentIdentifier" : "BJNR390800994BJNE000600307",
          "paragraph" : "Anlage 2",
          "title" : "(zu § 2 Abs. 3)"
        }
      ],
      "sectionNumber" : {
        "numbers" : [
          1
        ]
      },
      "subsections" : [

      ],
      "title" : "Inhalt"
    }
  ]
}